pmbec_align.c
setup.py
test/__init__.py
test/data.py
test/test_performance.py
test/test_topeology.py
topeology/__init__.py
topeology/calculate.py
topeology/iedb_data.py
topeology/pmbec.py
topeology/scorers.py
topeology/shell.py
topeology.egg-info/PKG-INFO
topeology.egg-info/SOURCES.txt
topeology.egg-info/dependency_links.txt
topeology.egg-info/entry_points.txt
topeology.egg-info/requires.txt
topeology.egg-info/top_level.txt