Metadata-Version: 1.1
Name: topeology
Version: 0.0.2
Summary: Compare epitope homology
Home-page: https://github.com/hammerlab/topeology
Author: Tavi Nathanson
Author-email: tavi {dot} nathanson {at} gmail {dot} com
License: http://www.apache.org/licenses/LICENSE-2.0.html
Platform: UNKNOWN
Classifier: Development Status :: 3 - Alpha
Classifier: Environment :: Console
Classifier: Operating System :: OS Independent
Classifier: Intended Audience :: Science/Research
Classifier: License :: OSI Approved :: Apache Software License
Classifier: Programming Language :: Python
Classifier: Topic :: Scientific/Engineering :: Bio-Informatics
